{
    "stageReward": {
        "questStageMstId": 100011,
        "clearCount": 0,
        "completeStatus": false,
        "stampRewardList": [
            {
                "questStageRewardMstId": 3167,
                "objectType": 1,
                "objectId": 26,
                "num": 1,
                "rarity": 2,
                "pickupFlg": false,
                "getStatus": false
            },
            {
                "questStageRewardMstId": 3168,
                "objectType": 1,
                "objectId": 26,
                "num": 1,
                "rarity": 2,
                "pickupFlg": false,
                "getStatus": false
            },
            {
                "questStageRewardMstId": 3169,
                "objectType": 1,
                "objectId": 26,
                "num": 1,
                "rarity": 2,
                "pickupFlg": false,
                "getStatus": false
            },
            {
                "questStageRewardMstId": 3170,
                "objectType": 1,
                "objectId": 26,
                "num": 1,
                "rarity": 2,
                "pickupFlg": false,
                "getStatus": false
            },
            {
                "questStageRewardMstId": 3171,
                "objectType": 1,
                "objectId": 26,
                "num": 1,
                "rarity": 2,
                "pickupFlg": false,
                "getStatus": false
            }
        ],
        "stampNextReward": {
            "questStageRewardMstId": 3167,
            "objectType": 1,
            "objectId": 26,
            "num": 1,
            "remainCount": 1,
            "rarity": 2,
            "pickupFlg": false
        }
    },
    "stageData": {
        "stageData": {
            "questStageId": 100011,
            "stageStatus": 1,
            "clearRewardObjectType": 14,
            "clearRewardObjectId": 0,
            "clearRewardNum": 1,
            "isStageRewardComplete": false,
            "hasGotFirstReward": false,
            "totalPowerThreshold": 0
        },
        "stageNextReward": {
            "questStageMstId": 100011,
            "objectType": 1,
            "objectId": 26,
            "num": 1,
            "isLast": false
        },
        "dropRewardList": [
            {
                "objectType": 2,
                "objectId": 366,
                "num": 1,
                "rarity": 1
            },
            {
                "objectType": 1,
                "objectId": 25,
                "num": 1,
                "rarity": 1
            },
            {
                "objectType": 1,
                "objectId": 26,
                "num": 1,
                "rarity": 2
            },
            {
                "objectType": 2,
                "objectId": 367,
                "num": 1,
                "rarity": 2
            }
        ],
        "campaignList": [],
        "cardBonusRewardList": []
    },
    "deckData": {
        "deckDataIdList": []
    }
}