{
    "stageReward": {
        "questStageMstId": 1044,
        "clearCount": 0,
        "completeStatus": false,
        "stampRewardList": null,
        "stampNextReward": null
    },
    "stageData": {
        "stageData": {
            "questStageId": 1044,
            "stageStatus": 1,
            "clearRewardObjectType": 14,
            "clearRewardObjectId": 0,
            "clearRewardNum": 1,
            "isStageRewardComplete": false,
            "hasGotFirstReward": false,
            "totalPowerThreshold": 0
        },
        "stageNextReward": null,
        "dropRewardList": [
            {
                "objectType": 1,
                "objectId": 19,
                "num": 1,
                "rarity": 2
            },
            {
                "objectType": 2,
                "objectId": 368,
                "num": 1,
                "rarity": 3
            },
            {
                "objectType": 2,
                "objectId": 362,
                "num": 1,
                "rarity": 2
            },
            {
                "objectType": 2,
                "objectId": 490,
                "num": 1,
                "rarity": 3
            }
        ],
        "campaignList": [],
        "cardBonusRewardList": []
    },
    "deckData": {
        "deckDataIdList": []
    }
}