{
    "stageReward": {
        "questStageMstId": 1430,
        "clearCount": 0,
        "completeStatus": false,
        "stampRewardList": [
            {
                "questStageRewardMstId": 396,
                "objectType": 14,
                "objectId": 0,
                "num": 2,
                "rarity": 0,
                "pickupFlg": false,
                "getStatus": false
            },
            {
                "questStageRewardMstId": 397,
                "objectType": 2,
                "objectId": 376,
                "num": 1,
                "rarity": 3,
                "pickupFlg": false,
                "getStatus": false
            },
            {
                "questStageRewardMstId": 398,
                "objectType": 2,
                "objectId": 382,
                "num": 1,
                "rarity": 3,
                "pickupFlg": false,
                "getStatus": false
            },
            {
                "questStageRewardMstId": 399,
                "objectType": 2,
                "objectId": 383,
                "num": 1,
                "rarity": 4,
                "pickupFlg": false,
                "getStatus": false
            },
            {
                "questStageRewardMstId": 400,
                "objectType": 14,
                "objectId": 0,
                "num": 2,
                "rarity": 0,
                "pickupFlg": false,
                "getStatus": false
            },
            {
                "questStageRewardMstId": 401,
                "objectType": 2,
                "objectId": 382,
                "num": 1,
                "rarity": 3,
                "pickupFlg": false,
                "getStatus": false
            },
            {
                "questStageRewardMstId": 402,
                "objectType": 2,
                "objectId": 364,
                "num": 1,
                "rarity": 4,
                "pickupFlg": false,
                "getStatus": false
            },
            {
                "questStageRewardMstId": 403,
                "objectType": 2,
                "objectId": 382,
                "num": 1,
                "rarity": 3,
                "pickupFlg": false,
                "getStatus": false
            },
            {
                "questStageRewardMstId": 404,
                "objectType": 2,
                "objectId": 399,
                "num": 1,
                "rarity": 4,
                "pickupFlg": false,
                "getStatus": false
            },
            {
                "questStageRewardMstId": 405,
                "objectType": 14,
                "objectId": 0,
                "num": 2,
                "rarity": 0,
                "pickupFlg": false,
                "getStatus": false
            }
        ],
        "stampNextReward": {
            "questStageRewardMstId": 396,
            "objectType": 14,
            "objectId": 0,
            "num": 2,
            "remainCount": 1,
            "rarity": 0,
            "pickupFlg": false
        }
    },
    "stageData": {
        "stageData": {
            "questStageId": 1430,
            "stageStatus": 1,
            "clearRewardObjectType": 14,
            "clearRewardObjectId": 0,
            "clearRewardNum": 1,
            "isStageRewardComplete": false,
            "hasGotFirstReward": false,
            "totalPowerThreshold": 20000
        },
        "stageNextReward": {
            "questStageMstId": 1430,
            "objectType": 14,
            "objectId": 0,
            "num": 2,
            "isLast": false
        },
        "dropRewardList": [
            {
                "objectType": 2,
                "objectId": 398,
                "num": 1,
                "rarity": 3
            },
            {
                "objectType": 2,
                "objectId": 363,
                "num": 1,
                "rarity": 3
            },
            {
                "objectType": 2,
                "objectId": 663,
                "num": 1,
                "rarity": 4
            }
        ],
        "campaignList": [],
        "cardBonusRewardList": []
    },
    "deckData": {
        "deckDataIdList": []
    }
}