{
    "stageReward": {
        "questStageMstId": 1513,
        "clearCount": 0,
        "completeStatus": false,
        "stampRewardList": [
            {
                "questStageRewardMstId": 1226,
                "objectType": 14,
                "objectId": 0,
                "num": 1,
                "rarity": 0,
                "pickupFlg": false,
                "getStatus": false
            },
            {
                "questStageRewardMstId": 1227,
                "objectType": 14,
                "objectId": 0,
                "num": 1,
                "rarity": 0,
                "pickupFlg": false,
                "getStatus": false
            },
            {
                "questStageRewardMstId": 1228,
                "objectType": 14,
                "objectId": 0,
                "num": 1,
                "rarity": 0,
                "pickupFlg": false,
                "getStatus": false
            },
            {
                "questStageRewardMstId": 1229,
                "objectType": 14,
                "objectId": 0,
                "num": 1,
                "rarity": 0,
                "pickupFlg": false,
                "getStatus": false
            },
            {
                "questStageRewardMstId": 1230,
                "objectType": 14,
                "objectId": 0,
                "num": 1,
                "rarity": 0,
                "pickupFlg": false,
                "getStatus": false
            },
            {
                "questStageRewardMstId": 1231,
                "objectType": 14,
                "objectId": 0,
                "num": 1,
                "rarity": 0,
                "pickupFlg": false,
                "getStatus": false
            },
            {
                "questStageRewardMstId": 1232,
                "objectType": 14,
                "objectId": 0,
                "num": 1,
                "rarity": 0,
                "pickupFlg": false,
                "getStatus": false
            },
            {
                "questStageRewardMstId": 1233,
                "objectType": 14,
                "objectId": 0,
                "num": 1,
                "rarity": 0,
                "pickupFlg": false,
                "getStatus": false
            },
            {
                "questStageRewardMstId": 1234,
                "objectType": 14,
                "objectId": 0,
                "num": 1,
                "rarity": 0,
                "pickupFlg": false,
                "getStatus": false
            },
            {
                "questStageRewardMstId": 1235,
                "objectType": 14,
                "objectId": 0,
                "num": 1,
                "rarity": 0,
                "pickupFlg": false,
                "getStatus": false
            },
            {
                "questStageRewardMstId": 1236,
                "objectType": 14,
                "objectId": 0,
                "num": 1,
                "rarity": 0,
                "pickupFlg": false,
                "getStatus": false
            },
            {
                "questStageRewardMstId": 1237,
                "objectType": 14,
                "objectId": 0,
                "num": 1,
                "rarity": 0,
                "pickupFlg": false,
                "getStatus": false
            },
            {
                "questStageRewardMstId": 1238,
                "objectType": 14,
                "objectId": 0,
                "num": 1,
                "rarity": 0,
                "pickupFlg": false,
                "getStatus": false
            },
            {
                "questStageRewardMstId": 1239,
                "objectType": 14,
                "objectId": 0,
                "num": 1,
                "rarity": 0,
                "pickupFlg": false,
                "getStatus": false
            },
            {
                "questStageRewardMstId": 1240,
                "objectType": 14,
                "objectId": 0,
                "num": 1,
                "rarity": 0,
                "pickupFlg": false,
                "getStatus": false
            },
            {
                "questStageRewardMstId": 1241,
                "objectType": 14,
                "objectId": 0,
                "num": 1,
                "rarity": 0,
                "pickupFlg": false,
                "getStatus": false
            },
            {
                "questStageRewardMstId": 1242,
                "objectType": 14,
                "objectId": 0,
                "num": 1,
                "rarity": 0,
                "pickupFlg": false,
                "getStatus": false
            },
            {
                "questStageRewardMstId": 1243,
                "objectType": 14,
                "objectId": 0,
                "num": 1,
                "rarity": 0,
                "pickupFlg": false,
                "getStatus": false
            },
            {
                "questStageRewardMstId": 1244,
                "objectType": 14,
                "objectId": 0,
                "num": 1,
                "rarity": 0,
                "pickupFlg": false,
                "getStatus": false
            },
            {
                "questStageRewardMstId": 1245,
                "objectType": 14,
                "objectId": 0,
                "num": 1,
                "rarity": 0,
                "pickupFlg": false,
                "getStatus": false
            }
        ],
        "stampNextReward": {
            "questStageRewardMstId": 1226,
            "objectType": 14,
            "objectId": 0,
            "num": 1,
            "remainCount": 1,
            "rarity": 0,
            "pickupFlg": false
        }
    },
    "stageData": {
        "stageData": {
            "questStageId": 1513,
            "stageStatus": 1,
            "clearRewardObjectType": 1,
            "clearRewardObjectId": 24,
            "clearRewardNum": 1,
            "isStageRewardComplete": false,
            "hasGotFirstReward": false,
            "totalPowerThreshold": 50000
        },
        "stageNextReward": {
            "questStageMstId": 1513,
            "objectType": 14,
            "objectId": 0,
            "num": 1,
            "isLast": false
        },
        "dropRewardList": [
            {
                "objectType": 2,
                "objectId": 773,
                "num": 1,
                "rarity": 5
            }
        ],
        "campaignList": [],
        "cardBonusRewardList": []
    },
    "deckData": {
        "deckDataIdList": []
    }
}