{
    "stageReward": {
        "questStageMstId": 2583,
        "clearCount": 0,
        "completeStatus": false,
        "stampRewardList": [
            {
                "questStageRewardMstId": 4747,
                "objectType": 2,
                "objectId": 368,
                "num": 3,
                "rarity": 3,
                "pickupFlg": false,
                "getStatus": false
            },
            {
                "questStageRewardMstId": 4748,
                "objectType": 2,
                "objectId": 368,
                "num": 3,
                "rarity": 3,
                "pickupFlg": false,
                "getStatus": false
            },
            {
                "questStageRewardMstId": 4749,
                "objectType": 2,
                "objectId": 368,
                "num": 3,
                "rarity": 3,
                "pickupFlg": false,
                "getStatus": false
            },
            {
                "questStageRewardMstId": 4750,
                "objectType": 2,
                "objectId": 368,
                "num": 3,
                "rarity": 3,
                "pickupFlg": false,
                "getStatus": false
            },
            {
                "questStageRewardMstId": 4751,
                "objectType": 2,
                "objectId": 368,
                "num": 3,
                "rarity": 3,
                "pickupFlg": false,
                "getStatus": false
            },
            {
                "questStageRewardMstId": 4752,
                "objectType": 1,
                "objectId": 26,
                "num": 1,
                "rarity": 2,
                "pickupFlg": false,
                "getStatus": false
            },
            {
                "questStageRewardMstId": 4753,
                "objectType": 1,
                "objectId": 26,
                "num": 1,
                "rarity": 2,
                "pickupFlg": false,
                "getStatus": false
            },
            {
                "questStageRewardMstId": 4754,
                "objectType": 1,
                "objectId": 26,
                "num": 1,
                "rarity": 2,
                "pickupFlg": false,
                "getStatus": false
            },
            {
                "questStageRewardMstId": 4755,
                "objectType": 1,
                "objectId": 26,
                "num": 1,
                "rarity": 2,
                "pickupFlg": false,
                "getStatus": false
            },
            {
                "questStageRewardMstId": 4756,
                "objectType": 1,
                "objectId": 26,
                "num": 1,
                "rarity": 2,
                "pickupFlg": false,
                "getStatus": false
            },
            {
                "questStageRewardMstId": 4757,
                "objectType": 2,
                "objectId": 369,
                "num": 3,
                "rarity": 4,
                "pickupFlg": false,
                "getStatus": false
            },
            {
                "questStageRewardMstId": 4758,
                "objectType": 2,
                "objectId": 369,
                "num": 3,
                "rarity": 4,
                "pickupFlg": false,
                "getStatus": false
            },
            {
                "questStageRewardMstId": 4759,
                "objectType": 2,
                "objectId": 369,
                "num": 3,
                "rarity": 4,
                "pickupFlg": false,
                "getStatus": false
            },
            {
                "questStageRewardMstId": 4760,
                "objectType": 2,
                "objectId": 369,
                "num": 3,
                "rarity": 4,
                "pickupFlg": false,
                "getStatus": false
            },
            {
                "questStageRewardMstId": 4761,
                "objectType": 2,
                "objectId": 369,
                "num": 3,
                "rarity": 4,
                "pickupFlg": false,
                "getStatus": false
            },
            {
                "questStageRewardMstId": 4762,
                "objectType": 1,
                "objectId": 26,
                "num": 2,
                "rarity": 2,
                "pickupFlg": false,
                "getStatus": false
            },
            {
                "questStageRewardMstId": 4763,
                "objectType": 1,
                "objectId": 26,
                "num": 2,
                "rarity": 2,
                "pickupFlg": false,
                "getStatus": false
            },
            {
                "questStageRewardMstId": 4764,
                "objectType": 1,
                "objectId": 26,
                "num": 2,
                "rarity": 2,
                "pickupFlg": false,
                "getStatus": false
            },
            {
                "questStageRewardMstId": 4765,
                "objectType": 1,
                "objectId": 26,
                "num": 2,
                "rarity": 2,
                "pickupFlg": false,
                "getStatus": false
            },
            {
                "questStageRewardMstId": 4766,
                "objectType": 1,
                "objectId": 27,
                "num": 1,
                "rarity": 3,
                "pickupFlg": false,
                "getStatus": false
            }
        ],
        "stampNextReward": {
            "questStageRewardMstId": 4747,
            "objectType": 2,
            "objectId": 368,
            "num": 3,
            "remainCount": 1,
            "rarity": 3,
            "pickupFlg": false
        }
    },
    "stageData": {
        "stageData": {
            "questStageId": 2583,
            "stageStatus": 1,
            "clearRewardObjectType": 14,
            "clearRewardObjectId": 0,
            "clearRewardNum": 1,
            "isStageRewardComplete": false,
            "hasGotFirstReward": false,
            "totalPowerThreshold": 0
        },
        "stageNextReward": {
            "questStageMstId": 2583,
            "objectType": 2,
            "objectId": 368,
            "num": 3,
            "isLast": false
        },
        "dropRewardList": [
            {
                "objectType": 2,
                "objectId": 1678,
                "num": 1,
                "rarity": 3
            },
            {
                "objectType": 2,
                "objectId": 1672,
                "num": 1,
                "rarity": 3
            },
            {
                "objectType": 2,
                "objectId": 1699,
                "num": 1,
                "rarity": 3
            },
            {
                "objectType": 2,
                "objectId": 397,
                "num": 1,
                "rarity": 2
            }
        ],
        "campaignList": [],
        "cardBonusRewardList": []
    },
    "deckData": {
        "deckDataIdList": []
    },
    "sweepTicketsNum": 0,
    "sweepBonusOpen": 0,
    "sweepActivityOpen": 1
}