{
    "stageReward": {
        "questStageMstId": 2598,
        "clearCount": 0,
        "completeStatus": false,
        "stampRewardList": [
            {
                "questStageRewardMstId": 4987,
                "objectType": 2,
                "objectId": 363,
                "num": 1,
                "rarity": 3,
                "pickupFlg": false,
                "getStatus": false
            },
            {
                "questStageRewardMstId": 4988,
                "objectType": 2,
                "objectId": 363,
                "num": 1,
                "rarity": 3,
                "pickupFlg": false,
                "getStatus": false
            },
            {
                "questStageRewardMstId": 4989,
                "objectType": 2,
                "objectId": 363,
                "num": 1,
                "rarity": 3,
                "pickupFlg": false,
                "getStatus": false
            },
            {
                "questStageRewardMstId": 4990,
                "objectType": 2,
                "objectId": 363,
                "num": 1,
                "rarity": 3,
                "pickupFlg": false,
                "getStatus": false
            },
            {
                "questStageRewardMstId": 4991,
                "objectType": 2,
                "objectId": 363,
                "num": 1,
                "rarity": 3,
                "pickupFlg": false,
                "getStatus": false
            }
        ],
        "stampNextReward": {
            "questStageRewardMstId": 4987,
            "objectType": 2,
            "objectId": 363,
            "num": 1,
            "remainCount": 1,
            "rarity": 3,
            "pickupFlg": false
        }
    },
    "stageData": {
        "stageData": {
            "questStageId": 2598,
            "stageStatus": 1,
            "clearRewardObjectType": 14,
            "clearRewardObjectId": 0,
            "clearRewardNum": 1,
            "isStageRewardComplete": false,
            "hasGotFirstReward": false,
            "totalPowerThreshold": 0
        },
        "stageNextReward": {
            "questStageMstId": 2598,
            "objectType": 2,
            "objectId": 363,
            "num": 1,
            "isLast": false
        },
        "dropRewardList": [
            {
                "objectType": 1,
                "objectId": 490,
                "num": 18,
                "rarity": 1
            }
        ],
        "campaignList": [],
        "cardBonusRewardList": []
    },
    "deckData": {
        "deckDataIdList": []
    },
    "sweepTicketsNum": 0,
    "sweepBonusOpen": 0,
    "sweepActivityOpen": 1
}