{
    "stageReward": {
        "questStageMstId": 2882,
        "clearCount": 0,
        "completeStatus": false,
        "stampRewardList": [
            {
                "questStageRewardMstId": 6385,
                "objectType": 14,
                "objectId": 0,
                "num": 1,
                "rarity": 0,
                "pickupFlg": false,
                "getStatus": false
            },
            {
                "questStageRewardMstId": 6386,
                "objectType": 14,
                "objectId": 0,
                "num": 1,
                "rarity": 0,
                "pickupFlg": false,
                "getStatus": false
            },
            {
                "questStageRewardMstId": 6387,
                "objectType": 14,
                "objectId": 0,
                "num": 1,
                "rarity": 0,
                "pickupFlg": false,
                "getStatus": false
            },
            {
                "questStageRewardMstId": 6388,
                "objectType": 14,
                "objectId": 0,
                "num": 1,
                "rarity": 0,
                "pickupFlg": false,
                "getStatus": false
            },
            {
                "questStageRewardMstId": 6389,
                "objectType": 14,
                "objectId": 0,
                "num": 1,
                "rarity": 0,
                "pickupFlg": false,
                "getStatus": false
            },
            {
                "questStageRewardMstId": 6390,
                "objectType": 14,
                "objectId": 0,
                "num": 1,
                "rarity": 0,
                "pickupFlg": false,
                "getStatus": false
            },
            {
                "questStageRewardMstId": 6391,
                "objectType": 14,
                "objectId": 0,
                "num": 1,
                "rarity": 0,
                "pickupFlg": false,
                "getStatus": false
            },
            {
                "questStageRewardMstId": 6392,
                "objectType": 14,
                "objectId": 0,
                "num": 1,
                "rarity": 0,
                "pickupFlg": false,
                "getStatus": false
            },
            {
                "questStageRewardMstId": 6393,
                "objectType": 14,
                "objectId": 0,
                "num": 1,
                "rarity": 0,
                "pickupFlg": false,
                "getStatus": false
            },
            {
                "questStageRewardMstId": 6394,
                "objectType": 14,
                "objectId": 0,
                "num": 1,
                "rarity": 0,
                "pickupFlg": false,
                "getStatus": false
            },
            {
                "questStageRewardMstId": 6395,
                "objectType": 14,
                "objectId": 0,
                "num": 1,
                "rarity": 0,
                "pickupFlg": false,
                "getStatus": false
            },
            {
                "questStageRewardMstId": 6396,
                "objectType": 14,
                "objectId": 0,
                "num": 1,
                "rarity": 0,
                "pickupFlg": false,
                "getStatus": false
            },
            {
                "questStageRewardMstId": 6397,
                "objectType": 14,
                "objectId": 0,
                "num": 1,
                "rarity": 0,
                "pickupFlg": false,
                "getStatus": false
            },
            {
                "questStageRewardMstId": 6398,
                "objectType": 14,
                "objectId": 0,
                "num": 1,
                "rarity": 0,
                "pickupFlg": false,
                "getStatus": false
            },
            {
                "questStageRewardMstId": 6399,
                "objectType": 14,
                "objectId": 0,
                "num": 1,
                "rarity": 0,
                "pickupFlg": false,
                "getStatus": false
            },
            {
                "questStageRewardMstId": 6400,
                "objectType": 14,
                "objectId": 0,
                "num": 1,
                "rarity": 0,
                "pickupFlg": false,
                "getStatus": false
            },
            {
                "questStageRewardMstId": 6401,
                "objectType": 14,
                "objectId": 0,
                "num": 1,
                "rarity": 0,
                "pickupFlg": false,
                "getStatus": false
            },
            {
                "questStageRewardMstId": 6402,
                "objectType": 14,
                "objectId": 0,
                "num": 1,
                "rarity": 0,
                "pickupFlg": false,
                "getStatus": false
            },
            {
                "questStageRewardMstId": 6403,
                "objectType": 14,
                "objectId": 0,
                "num": 1,
                "rarity": 0,
                "pickupFlg": false,
                "getStatus": false
            },
            {
                "questStageRewardMstId": 6404,
                "objectType": 14,
                "objectId": 0,
                "num": 1,
                "rarity": 0,
                "pickupFlg": false,
                "getStatus": false
            }
        ],
        "stampNextReward": {
            "questStageRewardMstId": 6385,
            "objectType": 14,
            "objectId": 0,
            "num": 1,
            "remainCount": 1,
            "rarity": 0,
            "pickupFlg": false
        }
    },
    "stageData": {
        "stageData": {
            "questStageId": 2882,
            "stageStatus": 1,
            "clearRewardObjectType": 1,
            "clearRewardObjectId": 28,
            "clearRewardNum": 1,
            "isStageRewardComplete": false,
            "hasGotFirstReward": false,
            "totalPowerThreshold": 80000
        },
        "stageNextReward": {
            "questStageMstId": 2882,
            "objectType": 14,
            "objectId": 0,
            "num": 1,
            "isLast": false
        },
        "dropRewardList": [
            {
                "objectType": 2,
                "objectId": 2104,
                "num": 1,
                "rarity": 5
            }
        ],
        "campaignList": [],
        "cardBonusRewardList": []
    },
    "deckData": {
        "deckDataIdList": []
    },
    "sweepTicketsNum": 0,
    "sweepBonusOpen": 0,
    "sweepActivityOpen": 1
}