{
    "stageReward": {
        "questStageMstId": 2897,
        "clearCount": 0,
        "completeStatus": false,
        "stampRewardList": [
            {
                "questStageRewardMstId": 6835,
                "objectType": 2,
                "objectId": 363,
                "num": 1,
                "rarity": 3,
                "pickupFlg": false,
                "getStatus": false
            },
            {
                "questStageRewardMstId": 6836,
                "objectType": 2,
                "objectId": 363,
                "num": 1,
                "rarity": 3,
                "pickupFlg": false,
                "getStatus": false
            },
            {
                "questStageRewardMstId": 6837,
                "objectType": 2,
                "objectId": 363,
                "num": 1,
                "rarity": 3,
                "pickupFlg": false,
                "getStatus": false
            },
            {
                "questStageRewardMstId": 6838,
                "objectType": 2,
                "objectId": 363,
                "num": 1,
                "rarity": 3,
                "pickupFlg": false,
                "getStatus": false
            },
            {
                "questStageRewardMstId": 6839,
                "objectType": 2,
                "objectId": 363,
                "num": 1,
                "rarity": 3,
                "pickupFlg": false,
                "getStatus": false
            }
        ],
        "stampNextReward": {
            "questStageRewardMstId": 6835,
            "objectType": 2,
            "objectId": 363,
            "num": 1,
            "remainCount": 1,
            "rarity": 3,
            "pickupFlg": false
        }
    },
    "stageData": {
        "stageData": {
            "questStageId": 2897,
            "stageStatus": 1,
            "clearRewardObjectType": 2,
            "clearRewardObjectId": 2120,
            "clearRewardNum": 1,
            "isStageRewardComplete": false,
            "hasGotFirstReward": false,
            "totalPowerThreshold": 0
        },
        "stageNextReward": {
            "questStageMstId": 2897,
            "objectType": 2,
            "objectId": 363,
            "num": 1,
            "isLast": false
        },
        "dropRewardList": [
            {
                "objectType": 1,
                "objectId": 607,
                "num": 14,
                "rarity": 1
            }
        ],
        "campaignList": [],
        "cardBonusRewardList": []
    },
    "deckData": {
        "deckDataIdList": []
    },
    "sweepTicketsNum": 0,
    "sweepBonusOpen": 0,
    "sweepActivityOpen": 1
}